MANIFEST.in
manage.py
setup.py
app/__init__.py
app/config_default.py
app/config_docker_example.py
app/config_example.py
app/config_test.py
app/database/__init__.py
app/database/base.py
app/database/model.py
app/static/dist/webhook.bundle.js
app/static/res/css/common.css
app/static/res/css/index.css
app/static/res/css/prism.css
app/static/res/img/bg0.jpg
app/static/res/img/bg1.jpg
app/static/res/img/bg2.jpg
app/static/res/img/bg3.jpg
app/static/res/img/bg4.jpg
app/static/res/img/history.png
app/static/res/img/index.png
app/static/res/img/logo.png
app/static/res/img/server.png
app/static/res/img/webhook.png
app/static/res/js/x-return-top.min.js
app/tasks/__init__.py
app/tasks/tasks.py
app/templates/404.html
app/templates/502.html
app/templates/index.html
app/utils/AuthUtil.py
app/utils/DateUtil.py
app/utils/HookDataParse.py
app/utils/JsonUtil.py
app/utils/RequestUtil.py
app/utils/ResponseUtil.py
app/utils/SshUtil.py
app/utils/StringUtil.py
app/utils/__init__.py
app/utils/validator.py
app/views/__init__.py
app/views/api.py
app/views/collaborator.py
app/views/common.py
app/views/history.py
app/views/server.py
app/views/socket.py
app/views/webhook.py
app/wraps/__init__.py
app/wraps/login_wrap.py
git_webhook.egg-info/PKG-INFO
git_webhook.egg-info/SOURCES.txt
git_webhook.egg-info/dependency_links.txt
git_webhook.egg-info/entry_points.txt
git_webhook.egg-info/not-zip-safe
git_webhook.egg-info/requires.txt
git_webhook.egg-info/top_level.txt